AUTHORS
COPYING-LGPL
COPYING-MIT
ChangeLog
INSTALL.rst
MANIFEST.in
Makefile
README.md
requirements-dev.txt
setup.py
winbuild.py
doc/callbacks.rst
doc/conf.py
doc/curl.rst
doc/curlmultiobject.rst
doc/curlobject.rst
doc/curlshareobject.rst
doc/files.rst
doc/index.rst
doc/install.rst
doc/internals.rst
doc/pycurl.rst
doc/quickstart.rst
doc/release-notes.rst
doc/release-process.rst
doc/thread-safety.rst
doc/troubleshooting.rst
doc/unicode.rst
doc/unimplemented.rst
doc/docstrings/curl.rst
doc/docstrings/curl_close.rst
doc/docstrings/curl_errstr.rst
doc/docstrings/curl_errstr_raw.rst
doc/docstrings/curl_getinfo.rst
doc/docstrings/curl_getinfo_raw.rst
doc/docstrings/curl_pause.rst
doc/docstrings/curl_perform.rst
doc/docstrings/curl_perform_rb.rst
doc/docstrings/curl_perform_rs.rst
doc/docstrings/curl_reset.rst
doc/docstrings/curl_set_ca_certs.rst
doc/docstrings/curl_setopt.rst
doc/docstrings/curl_setopt_string.rst
doc/docstrings/curl_unsetopt.rst
doc/docstrings/multi.rst
doc/docstrings/multi_add_handle.rst
doc/docstrings/multi_assign.rst
doc/docstrings/multi_close.rst
doc/docstrings/multi_fdset.rst
doc/docstrings/multi_info_read.rst
doc/docstrings/multi_perform.rst
doc/docstrings/multi_remove_handle.rst
doc/docstrings/multi_select.rst
doc/docstrings/multi_setopt.rst
doc/docstrings/multi_socket_action.rst
doc/docstrings/multi_socket_all.rst
doc/docstrings/multi_timeout.rst
doc/docstrings/pycurl_global_cleanup.rst
doc/docstrings/pycurl_global_init.rst
doc/docstrings/pycurl_module.rst
doc/docstrings/pycurl_version_info.rst
doc/docstrings/share.rst
doc/docstrings/share_close.rst
doc/docstrings/share_setopt.rst
doc/static/favicon.ico
examples/basicfirst.py
examples/file_upload.py
examples/linksys.py
examples/opensocketexception.py
examples/retriever-multi.py
examples/retriever.py
examples/sfquery.py
examples/smtp.py
examples/ssh_keyfunction.py
examples/xmlrpc_curl.py
examples/quickstart/file_upload_buffer.py
examples/quickstart/file_upload_real.py
pycurl_oqs.egg-info/PKG-INFO
pycurl_oqs.egg-info/SOURCES.txt
pycurl_oqs.egg-info/dependency_links.txt
pycurl_oqs.egg-info/top_level.txt
